{
  "leaderboard": [
    {
      "id": 1,
      "name": "Bronwyn Smit",
      "description": "Western Cape",
      "overall_score": "92",
      "avatar": "https://www.gravatar.com/avatar/205e460b479e2e5b48aec07710c08d50.jpg"
    },
    {
      "id": 2,
      "name": "Bronwyn Smit2",
      "description": "Western Cape2",
      "overall_score": "93",
      "avatar": "https://www.gravatar.com/avatar/205e460b479e2e5b48aec07710c08d50.jpg"
    },
    {
      "id": 3,
      "name": "Bronwyn Smit3",
      "description": "Western Cape3",
      "overall_score": "54",
      "avatar": "https://www.gravatar.com/avatar/205e460b479e2e5b48aec07710c08d50.jpg"
    },
    {
      "id": 4,
      "name": "Bronwyn Smit4",
      "description": "Western Cape4",
      "overall_score": "12",
      "avatar": "https://www.gravatar.com/avatar/205e460b479e2e5b48aec07710c08d50.jpg"
    },
    {
      "id": 5,
      "name": "Bronwyn Smit5",
      "description": "Western Cape5",
      "overall_score": "35",
      "avatar": "https://www.gravatar.com/avatar/205e460b479e2e5b48aec07710c08d50.jpg"
    },
    {
       "id": 6,
      "name": "Bronwyn Smit6",
      "description": "Western Cape6",
      "overall_score": "36"
    },
    {
       "id": 7,
      "name": "Bronwyn Smit7",
      "description": "Western Cape7",
      "overall_score": "68"
    },
    {
      "id": 8,
      "name": "Bronwyn Smit",
      "description": "Western Cape",
      "overall_score": "99",
      "avatar": "https://www.gravatar.com/avatar/205e460b479e2e5b48aec07710c08d50.jpg"
    },
    {
      "id": 9,
      "name": "Bronwyn Smit",
      "description": "Western Cape",
      "overall_score": "92",
      "avatar": "https://www.gravatar.com/avatar/205e460b479e2e5b48aec07710c08d50.jpg"
    }
  ],
  "trends": {
    "months": ["Jan", "Feb", "Mar", "Apr"],
    "data": [
      {
        "name": "Checkers Moreleta Park",
        "overall_score": [
          70,
          80,
          90,
          94
        ] 
      },
      {
        "name": "Checkers - Inland East - S1",
        "overall_score": [
          75,
          91,
          83,
          64
        ] 
      }
    ]
  },
  "historyList": [
    {
      "id": 1,
      "form_name": "Touch Points",
      "overall_score": 75,
      "created_at": "2022-01-28"
    },
    {
      "id": 2,
      "form_name": "Touch Points",
      "overall_score": 35,
      "created_at": "2022-02-28"
    },
    {
      "id": 3,
      "form_name": "Touch Points",
      "overall_score": 87,
      "created_at": "2022-03-28"
    },
    {
      "id": 4,
      "form_name": "Touch Points",
      "overall_score": 46,
      "created_at": "2022-04-28"
    }
  ],
  "historyDetail": {
    "status": "success",
    "message": "Form submitted successfully",
    "form_submission_id": 118,
    "form_name": "Touchpoints",
    "overall_score": "75",
    "feedback": [
        {
            "question_group_id": "1",
            "question_group": "Cold Shelf",
            "question_type": "sku_count",
            "question_text": "Indicate share of Danone assortment",
            "brand": "Danone",
            "completed_data": {
                "category_value": {
                    "Fruit": "30",
                    "Drinking": "30",
                    "Kids": "29",
                    "Cold Shelf": "42"
                },
                "market_targets": {
                    "Fruit": "42",
                    "Drinking": "42",
                    "Kids": "35",
                    "Cold Shelf": "50"
                },
                "fsi_values": {
                    "Fruit": "71",
                    "Drinking": "71",
                    "Kids": "83",
                    "Cold Shelf": "84"
                }
            }
        },
        {
            "question_group_id": "1",
            "question_group": "Cold Shelf",
            "question_type": "sku_select",
            "question_text": "Select all Hero and NPD SKUs on Cold Shelf",
            "products": [
                "YOGISIP YOGHURT DRINK BANANA 10X250G",
                "YOGISIP YOGHURT DRINK APRICOT 10X250G",
                "YOGISIP YOGHURT DRINK GRANADILLA 10X250G",
                "YOGISIP YOGHURT DRINK STRAWBERRY 10X250G",
                "YOGISIP YOG STRWBERRY MLPK 6X250G",
                "YOGISIP MIXED BERRY 10X250G",
                "YOGISIP YOG DRI W/UP STBERRY/OATS10X300G",
                "YOGISIP YOG DRINK STBERRY SUP,FRT10X300G",
                "YOGISIP YOGHURT DRINK CAPPUCINO 10X300G"
            ]
        },
        {
            "question_group_id": "2",
            "question_group": "Ambient Shelf",
            "question_type": "yes_no",
            "question_text": "Are Hero SKUs on Eye Level for Cold Shelf?",
            "answer": "No"
        }
    ]
  }
}